charmd/__init__.py
charmd/__main__.py
charmd-0.2.5.dist-info/licenses/LICENSE
charmd-0.2.5.dist-info/METADATA
charmd-0.2.5.dist-info/WHEEL
charmd-0.2.5.dist-info/entry_points.txt
charmd-0.2.5.dist-info/top_level.txt
charmd-0.2.5.dist-info/RECORD
