Metadata-Version: 2.4
Name: charmd
Version: 0.2.5
Summary: CLI to start a PyCharm debug session and then run a Python target in-process
Author: python-charmd contributors
License: MIT
Project-URL: Homepage, https://github.com/TekWizely/python-charmd
Project-URL: Repository, https://github.com/TekWizely/python-charmd
Project-URL: Issues, https://github.com/TekWizely/python-charmd/issues
Project-URL: Changelog, https://github.com/TekWizely/python-charmd/releases
Keywords: pycharm,debug,pydevd,debugger,cli
Classifier: Development Status :: 3 - Alpha
Classifier: Intended Audience :: Developers
Classifier: Topic :: Software Development :: Debuggers
Classifier: License :: OSI Approved :: MIT License
Classifier: Programming Language :: Python :: 3
Classifier: Programming Language :: Python :: 3 :: Only
Classifier: Programming Language :: Python :: 3.8
Classifier: Programming Language :: Python :: 3.9
Classifier: Programming Language :: Python :: 3.10
Classifier: Programming Language :: Python :: 3.11
Classifier: Programming Language :: Python :: 3.12
Classifier: Programming Language :: Python :: 3.13
Classifier: Environment :: Console
Classifier: Operating System :: OS Independent
Requires-Python: >=3.8
License-File: LICENSE
Provides-Extra: dev
Requires-Dist: pytest>=7.0.0; extra == "dev"
Requires-Dist: pytest-cov>=4.0.0; extra == "dev"
Requires-Dist: black>=23.0.0; extra == "dev"
Requires-Dist: ruff>=0.1.0; extra == "dev"
Requires-Dist: build>=1.0.0; extra == "dev"
Requires-Dist: twine>=4.0.0; extra == "dev"
Dynamic: license-file
